[
  {
    "ContainingType": "CapestoneProject.Controllers.AuthController",
    "Method": "Login",
    "RelativePath": "api/Auth/login",
    "HttpMethod": "POST",
    "IsController": true,
    "Order": 0,
    "Parameters": [
      {
        "Name": "input",
        "Type": "CapestoneProject.DTOs.Login.Request.LoginInputDTO",
        "IsRequired": true
      }
    ],
    "ReturnTypes": []
  },
  {
    "ContainingType": "CapestoneProject.Controllers.AuthController",
    "Method": "ResetPassword",
    "RelativePath": "api/Auth/reset-password",
    "HttpMethod": "POST",
    "IsController": true,
    "Order": 0,
    "Parameters": [
      {
        "Name": "input",
        "Type": "CapestoneProject.DTOs.ResetPassword.Request.ResetPasswordDTO",
        "IsRequired": true
      }
    ],
    "ReturnTypes": []
  },
  {
    "ContainingType": "CapestoneProject.Controllers.AuthController",
    "Method": "Signup",
    "RelativePath": "api/Auth/signup",
    "HttpMethod": "POST",
    "IsController": true,
    "Order": 0,
    "Parameters": [
      {
        "Name": "input",
        "Type": "CapestoneProject.DTOs.SignUp.Request.SignUpInputDTO",
        "IsRequired": true
      }
    ],
    "ReturnTypes": []
  }
]